scatseisnet/__init__.py
scatseisnet/inventory.py
scatseisnet/io.py
scatseisnet/network.py
scatseisnet/signal.py
scatseisnet/wavelet.py
scatseisnet/cli/__init__.py
scatseisnet/cli/cli.py
scatseisnet/cli/common.py
scatseisnet/cli/features.py
scatseisnet/cli/inventory.py
scatseisnet/cli/linkage.py
scatseisnet/cli/transform.py
scatseisnet/cli/waveforms.py
scatseisnet/display/__init__.py
scatseisnet/display/features.py
scatseisnet/display/inventory.py
scatseisnet/display/linkage.py
scatseisnet/display/scatterings.py
scatseisnet/display/waveforms.py
scatseisnet/hierarchy/__init__.py
scatseisnet/hierarchy/cluster.py
scatseisnet/hierarchy/display.py
scatseisnet_gpu-0.1.6.dist-info/METADATA
scatseisnet_gpu-0.1.6.dist-info/WHEEL
scatseisnet_gpu-0.1.6.dist-info/entry_points.txt
scatseisnet_gpu-0.1.6.dist-info/top_level.txt
scatseisnet_gpu-0.1.6.dist-info/RECORD
