Metadata-Version: 2.1
Name: scatseisnet-gpu
Version: 0.1.6
Summary: UNKNOWN
Home-page: UNKNOWN
License: UNKNOWN
Platform: UNKNOWN
Requires-Python: >=3.6, <4
Requires-Dist: astropy
Requires-Dist: click
Requires-Dist: fastcluster
Requires-Dist: nmmn
Requires-Dist: numpy
Requires-Dist: obspy
Requires-Dist: pandas
Requires-Dist: parse
Requires-Dist: seaborn
Requires-Dist: sklearn
Requires-Dist: tqdm
